zester
