Metadata-Version: 1.0
Name: zester
Version: 0.0.3
Summary: Easier Python client libraries
Home-page: https://github.com/spulec/zester
Author: Steve Pulec
Author-email: spulec@gmail
License: UNKNOWN
Platform: UNKNOWN
